a_pandas_ex_bs4df_lite/README.MD
a_pandas_ex_bs4df_lite/__init__.py
a_pandas_ex_bs4df_lite/requirements.txt
a_pandas_ex_bs4df_lite/thirdparty.json
a_pandas_ex_bs4df_lite-0.12.dist-info/LICENSE.rst
a_pandas_ex_bs4df_lite-0.12.dist-info/METADATA
a_pandas_ex_bs4df_lite-0.12.dist-info/WHEEL
a_pandas_ex_bs4df_lite-0.12.dist-info/top_level.txt
a_pandas_ex_bs4df_lite-0.12.dist-info/RECORD
