Metadata-Version: 2.1
Name: a-pandas-ex-bs4df-lite
Version: 0.12
Summary: Light version of a_pandas_ex_bs4df
Home-page: https://github.com/hansalemaos/a_pandas_ex_bs4df_lite
Author: Johannes Fischer
Author-email: aulasparticularesdealemaosp@gmail.com
License: MIT
Keywords: pandas,bs4,soup,webscraping
Classifier: Development Status :: 4 - Beta
Classifier: Programming Language :: Python :: 3 :: Only
Classifier: Programming Language :: Python :: 3.10
Classifier: Topic :: Software Development :: Libraries :: Python Modules
Classifier: Topic :: Utilities
License-File: LICENSE.rst
Requires-Dist: a-pandas-ex-apply-ignore-exceptions
Requires-Dist: beautifulsoup4
Requires-Dist: fake-headers
Requires-Dist: flatten-any-dict-iterable-or-whatsoever
Requires-Dist: lxml
Requires-Dist: pandas
Requires-Dist: requests
